wfarchive/__about__.py
wfarchive/__init__.py
wfarchive/cli.py
wfarchive/core.py
wfarchive/templates.py
wfarchive/typing.py
wfarchive-0.0.10.dist-info/METADATA
wfarchive-0.0.10.dist-info/WHEEL
wfarchive-0.0.10.dist-info/entry_points.txt
wfarchive-0.0.10.dist-info/licenses/LICENSE.txt
wfarchive-0.0.10.dist-info/RECORD
