Metadata-Version: 2.3
Name: wfarchive
Version: 0.0.10
Author-email: Heqi Zhang <zhangheqi@mail.ustc.edu.cn>
License-Expression: MIT
License-File: LICENSE.txt
Classifier: Development Status :: 4 - Beta
Classifier: Programming Language :: Python :: 3.9
Classifier: Programming Language :: Python :: 3.10
Classifier: Programming Language :: Python :: 3.11
Classifier: Programming Language :: Python :: 3.12
Requires-Python: >=3.9
Requires-Dist: requests
